{
  "language": "en-US",
  "region": "US",
  "quoteType": "ETF",
  "typeDisp": "ETF",
  "quoteSourceName": "Nasdaq Real Time Price",
  "triggerable": true,
  "customPriceAlertConfidence": "HIGH",
  "currency": "USD",
  "corporateActions": [],
  "postMarketTime": "2025-10-15T22:25:33.000Z",
  "regularMarketTime": "2025-10-15T20:00:01.000Z",
  "exchange": "NGM",
  "messageBoardId": "finmb_8108558",
  "exchangeTimezoneName": "America/New_York",
  "exchangeTimezoneShortName": "EDT",
  "gmtOffSetMilliseconds": -14400000,
  "market": "us_market",
  "esgPopulated": false,
  "regularMarketChangePercent": 0.7056807,
  "regularMarketPrice": 602.22,
  "shortName": "Invesco QQQ Trust, Series 1",
  "longName": "Invesco QQQ Trust",
  "trailingPE": 33.956715,
  "trailingAnnualDividendYield": 0.002959866,
  "dividendYield": 0.47,
  "ytdReturn": 17.91539,
  "trailingThreeMonthReturns": 8.94211,
  "trailingThreeMonthNavReturns": 8.94211,
  "netAssets": 385755185000,
  "epsTrailingTwelveMonths": 17.73493,
  "sharesOutstanding": 393100000,
  "bookValue": 357.774,
  "fiftyDayAverage": 585.195,
  "fiftyDayAverageChange": 17.024963,
  "fiftyDayAverageChangePercent": 0.029092804,
  "twoHundredDayAverage": 530.4136,
  "twoHundredDayAverageChange": 71.8064,
  "twoHundredDayAverageChangePercent": 0.13537812,
  "netExpenseRatio": 0.2,
  "marketCap": 236732678144,
  "priceToBook": 1.6832414,
  "sourceInterval": 15,
  "exchangeDataDelayedBy": 0,
  "tradeable": false,
  "cryptoTradeable": false,
  "marketState": "POST",
  "hasPrePostMarketData": true,
  "firstTradeDateMilliseconds": "1999-03-10T14:30:00.000Z",
  "priceHint": 2,
  "postMarketChangePercent": 0.19760261,
  "postMarketPrice": 603.41,
  "postMarketChange": 1.1900024,
  "regularMarketChange": 4.2199707,
  "regularMarketDayHigh": 606.7,
  "regularMarketDayRange": { "low": 595.94, "high": 606.7 },
  "regularMarketDayLow": 595.94,
  "regularMarketVolume": 62315340,
  "regularMarketPreviousClose": 598,
  "bid": 602.14,
  "ask": 602.69,
  "bidSize": 10,
  "askSize": 54,
  "fullExchangeName": "NasdaqGM",
  "financialCurrency": "USD",
  "regularMarketOpen": 604.01,
  "averageDailyVolume3Month": 49812159,
  "averageDailyVolume10Day": 56603930,
  "fiftyTwoWeekLowChange": 199.82996,
  "fiftyTwoWeekLowChangePercent": 0.49660763,
  "fiftyTwoWeekRange": { "low": 402.39, "high": 613.18 },
  "fiftyTwoWeekHighChange": -10.960022,
  "fiftyTwoWeekHighChangePercent": -0.01787407,
  "fiftyTwoWeekLow": 402.39,
  "fiftyTwoWeekHigh": 613.18,
  "fiftyTwoWeekChangePercent": 21.814585,
  "trailingAnnualDividendRate": 1.77,
  "symbol": "QQQ"
}
